{
  "author": "王旭;刘斌斌;邱均平.",
  "year": "2025",
  "title": "面向信息治理的生成式人工智能政策法规文本量化评价与优化研究",
  "journal": "情报学报",
  "keywords": "信息治理;生成式人工智能;政策法规;量化评价;PMC指数模型;优化框架",
  "abstract": "数智时代，生成式人工智能（generative artificial intelligence,GAI）已成为全球各界关注的焦点，其展现的大语言模型的涌现能力，引发了信息生态中的诸多乱象。量化评价并优化GAI政策法规，在丰富GAI治理学理化研究、助力提升社会风险治理水平与信息治理效能和推进国家网络空间治理等方面具有现实意义。本文首先剖析了GAI内容引发的信息治理困境，其次，采用PMC指数模型（policy modeling consistency index model）并结合Matlab工具，对全球14项GAI政策法规文本进行量化评价分析。研究发现，政策法规整体一致性水平较高，但仍存在立法行业领域服务类型不明确、可信可控性应用功能受限、技术保障治理范围固化的问题。据此，本文提出技术优化、风险评估、应用部署和国际政策法规交融4个优化层面；针对GAI引发的信息治理困境问题，将敏捷治理细化为智慧服务、可信应用和技术安全三大核心维度，以此作为评价GAI政策法规的标尺；构建了软硬法兼施的灵活方案和场景化分层治理模式的优化框架，并提出了以信息治理为导向的GAI政策法规优化建议。",
  "id": 3
}